.DS_Store
Icon
metaquantus/.DS_Store
metaquantus/Icon
metaquantus/__init__.py
metaquantus/benchmarking (1).py
metaquantus/benchmarking.py
metaquantus/meta_evaluation (1).py
metaquantus/meta_evaluation.py
metaquantus/helpers/Icon
metaquantus/helpers/__init__.py
metaquantus/helpers/configs.py
metaquantus/helpers/configs_utils.py
metaquantus/helpers/models.py
metaquantus/helpers/plotting.py
metaquantus/helpers/sanity_checks.py
metaquantus/helpers/utils.py
metaquantus/helpers/utils_quantus.py
metaquantus/perturbation_tests/Icon
metaquantus/perturbation_tests/__init__.py
metaquantus/perturbation_tests/base.py
metaquantus/perturbation_tests/input_perturbation_test (1).py
metaquantus/perturbation_tests/input_perturbation_test.py
metaquantus/perturbation_tests/ipt.py
metaquantus/perturbation_tests/model_perturbation_test (1).py
metaquantus/perturbation_tests/model_perturbation_test.py
metaquantus/perturbation_tests/mpt.py
tests/Icon
tests/__init__.py
tests/conftest.py
tests/test_benchmarking.py
tests/test_master.py
tests/test_meta_evaluation.py
metaquantus-0.0.5.dist-info/COPYING
metaquantus-0.0.5.dist-info/COPYING.LESSER
metaquantus-0.0.5.dist-info/Icon
metaquantus-0.0.5.dist-info/METADATA
metaquantus-0.0.5.dist-info/WHEEL
metaquantus-0.0.5.dist-info/top_level.txt
metaquantus-0.0.5.dist-info/RECORD
