Metadata-Version: 2.1
Name: metaquantus
Version: 0.0.5
Summary: MetaQuantus is a XAI performance tool for identifying reliable metrics.
Home-page: https://github.com/annahedstroem/MetaQuantus
Author: Anna Hedstrom
Author-email: hedstroem.anna@gmail.com
License: GNU LESSER GENERAL PUBLIC LICENSE VERSION 3
Keywords: explainable ai,evaluation,xai,machine learning,deep learning
Requires-Python: >=3.8
License-File: COPYING
License-File: COPYING.LESSER
Requires-Dist: cachetools ==5.3.1
Requires-Dist: captum >=0.6.0
Requires-Dist: timm >=0.6.12
Requires-Dist: torch >=2.0.0
Requires-Dist: torchvision >=0.15.1
Requires-Dist: pandas >=1.3.5
Requires-Dist: quantus >=0.4.3
